ramboo_tools/__init__.py
ramboo_tools/__version__.py
ramboo_tools/char_info.py
ramboo_tools/config.py
ramboo_tools/dictmatch.py
ramboo_tools/edit_distance.py
ramboo_tools/emoji_info.py
ramboo_tools/global_data.py
ramboo_tools/load_dict.py
ramboo_tools/pretty_printer.py
ramboo_tools/stream_processor.py
ramboo_tools/string_info.py
ramboo_tools/tf_idf.py
ramboo_tools/util.py
ramboo_tools/script/__init__.py
ramboo_tools/script/csv2txt.py
ramboo_tools/script/cut.py
ramboo_tools/script/edit_dis.py
ramboo_tools/script/expand_line.py
ramboo_tools/script/fzlftHuoxingDao.py
ramboo_tools/script/get_huoxing_map.py
ramboo_tools/script/get_word_frequency.py
ramboo_tools/script/get_zp_info.py
ramboo_tools/script/html_unescape.py
ramboo_tools/script/huoxing_client.py
ramboo_tools/script/model_test.py
ramboo_tools/script/pretty_print.py
ramboo_tools/script/strategy_report.py
ramboo_tools/script/text_match.py
ramboo_tools/script/txt2csv.py
ramboo_tools/script/txt2huoxing.py
ramboo_tools/script/txt2xls.py
ramboo_tools/script/txt2xls_v1.py
ramboo_tools/script/txt2xls_v2.py
ramboo_tools/script/xls2txt.py
ramboo_tools-0.0.2.dist-info/COPYING
ramboo_tools-0.0.2.dist-info/METADATA
ramboo_tools-0.0.2.dist-info/WHEEL
ramboo_tools-0.0.2.dist-info/entry_points.txt
ramboo_tools-0.0.2.dist-info/top_level.txt
ramboo_tools-0.0.2.dist-info/RECORD
