Metadata-Version: 2.1
Name: ramboo-tools
Version: 0.0.2
Summary: "RAMBOO's tools"
Home-page: https://github.com/RAMBOO1990/RAMBOO-tools
Author: RAMBOO
Author-email: ramboooo@126.com
License: UNKNOWN
Platform: UNKNOWN
Classifier: Intended Audience :: Developers
Classifier: Programming Language :: Python
Classifier: Programming Language :: Python :: 2
Classifier: Programming Language :: Python :: 2.7
Classifier: Programming Language :: Python :: 3
Classifier: Programming Language :: Python :: 3.8
Requires-Dist: six (<2.0.0,>=1.11.0)
Requires-Dist: pandas (>=1.2)
Requires-Dist: openpyxl (>=3.0)
Requires-Dist: xlwt (>=1.3)
Provides-Extra: dev
Requires-Dist: flake8 (<4.0.0,>=3.5.0) ; extra == 'dev'
Provides-Extra: test
